[["Story","Gathering","Ivalice","Bounties"],{"id":1,"icon":290,"cat":1,"name":"Cat Collector","desc":"Mrs. Buttersworth lost all of her cats. Can you find all five of them?","steps":[["Collect all 5 cats.",true,1,5,false],["Talk to Mrs. Buttersworth.",false,1,1,false]],"rewards":[["custom","Kiss from Mrs. Buttersworth",0,false],["item",1,5,false],["gold",100,0,false],["xp",100,0,false]]},{"id":2,"icon":575,"name":"Getting Milk for Mom","steps":[["get \"milk\" from Rage",true,21,1,false],["give 'milk' to mom",true,22,1,false]],"rewards":[["xp",100,1,false]],"cat":1,"desc":"<Description>"},{"id":3,"icon":-1,"name":"<Name>","steps":[["<Step>",false,1,1,false]],"rewards":[["item",1,1,false]],"cat":0,"desc":"<Description>"},{"id":4,"icon":-1,"name":"<Name>","steps":[["<Step>",false,1,1,false]],"rewards":[["item",1,1,false]],"cat":0,"desc":"<Description>"},{"id":5,"icon":-1,"name":"<Name>","steps":[["<Step>",false,1,1,false]],"rewards":[["item",1,1,false]],"cat":0,"desc":"<Description>"},{"id":6,"icon":-1,"name":"<Name>","steps":[["<Step>",false,1,1,false]],"rewards":[["item",1,1,false]],"cat":0,"desc":"<Description>"},{"id":7,"icon":-1,"name":"<Name>","steps":[["<Step>",false,1,1,false]],"rewards":[["item",1,1,false]],"cat":0,"desc":"<Description>"},{"id":8,"icon":-1,"name":"<Name>","steps":[["<Step>",false,1,1,false]],"rewards":[["item",1,1,false]],"cat":0,"desc":"<Description>"},{"id":9,"icon":-1,"name":"<Name>","steps":[["<Step>",false,1,1,false]],"rewards":[["item",1,1,false]],"cat":0,"desc":"<Description>"},{"id":10,"icon":-1,"name":"<Name>","steps":[["<Step>",false,1,1,false]],"rewards":[["item",1,1,false]],"cat":0,"desc":"<Description>"},{"id":11,"icon":-1,"name":"<Name>","steps":[["<Step>",false,1,1,false]],"rewards":[["item",1,1,false]],"cat":0,"desc":"<Description>"},{"id":12,"icon":-1,"name":"<Name>","steps":[["<Step>",false,1,1,false]],"rewards":[["item",1,1,false]],"cat":0,"desc":"<Description>"},{"id":13,"icon":-1,"name":"<Name>","steps":[["<Step>",false,1,1,false]],"rewards":[["item",1,1,false]],"cat":0,"desc":"<Description>"},{"id":14,"icon":-1,"name":"<Name>","steps":[["<Step>",false,1,1,false]],"rewards":[["item",1,1,false]],"cat":0,"desc":"<Description>"},{"id":15,"icon":-1,"name":"<Name>","steps":[["<Step>",false,1,1,false]],"rewards":[["item",1,1,false]],"cat":0,"desc":"<Description>"},{"id":16,"icon":-1,"name":"<Name>","steps":[["<Step>",false,1,1,false]],"rewards":[["item",1,1,false]],"cat":0,"desc":"<Description>"},{"id":17,"icon":-1,"name":"<Name>","steps":[["<Step>",false,1,1,false]],"rewards":[["item",1,1,false]],"cat":0,"desc":"<Description>"},{"id":18,"icon":-1,"name":"<Name>","steps":[["<Step>",false,1,1,false]],"rewards":[["item",1,1,false]],"cat":0,"desc":"<Description>"},{"id":19,"icon":-1,"name":"<Name>","steps":[["<Step>",false,1,1,false]],"rewards":[["item",1,1,false]],"cat":0,"desc":"<Description>"},{"id":20,"icon":-1,"name":"<Name>","steps":[["<Step>",false,1,1,false]],"rewards":[["item",1,1,false]],"cat":0,"desc":"<Description>"},{"id":21,"icon":-1,"name":"<Name>","steps":[["<Step>",false,1,1,false]],"rewards":[["item",1,1,false]],"cat":0,"desc":"<Description>"},{"id":22,"icon":-1,"name":"<Name>","steps":[["<Step>",false,1,1,false]],"rewards":[["item",1,1,false]],"cat":0,"desc":"<Description>"},{"id":23,"icon":-1,"name":"<Name>","steps":[["<Step>",false,1,1,false]],"rewards":[["item",1,1,false]],"cat":0,"desc":"<Description>"},{"id":24,"icon":-1,"name":"<Name>","steps":[["<Step>",false,1,1,false]],"rewards":[["item",1,1,false]],"cat":0,"desc":"<Description>"},{"id":25,"icon":-1,"name":"<Name>","steps":[["<Step>",false,1,1,false]],"rewards":[["item",1,1,false]],"cat":0,"desc":"<Description>"},{"id":26,"icon":-1,"name":"<Name>","steps":[["<Step>",false,1,1,false]],"rewards":[["item",1,1,false]],"cat":0,"desc":"<Description>"},{"id":27,"icon":-1,"name":"<Name>","steps":[["<Step>",false,1,1,false]],"rewards":[["item",1,1,false]],"cat":0,"desc":"<Description>"},{"id":28,"icon":-1,"name":"<Name>","steps":[["<Step>",false,1,1,false]],"rewards":[["item",1,1,false]],"cat":0,"desc":"<Description>"},{"id":29,"icon":-1,"name":"<Name>","steps":[["<Step>",false,1,1,false]],"rewards":[["item",1,1,false]],"cat":0,"desc":"<Description>"},{"id":30,"icon":-1,"name":"<Name>","steps":[["<Step>",false,1,1,false]],"rewards":[["item",1,1,false]],"cat":0,"desc":"<Description>"},{"id":31,"icon":-1,"name":"<Name>","steps":[["<Step>",false,1,1,false]],"rewards":[["item",1,1,false]],"cat":0,"desc":"<Description>"},{"id":32,"icon":-1,"name":"<Name>","steps":[["<Step>",false,1,1,false]],"rewards":[["item",1,1,false]],"cat":0,"desc":"<Description>"},{"id":33,"icon":-1,"name":"<Name>","steps":[["<Step>",false,1,1,false]],"rewards":[["item",1,1,false]],"cat":0,"desc":"<Description>"},{"id":34,"icon":-1,"name":"<Name>","steps":[["<Step>",false,1,1,false]],"rewards":[["item",1,1,false]],"cat":0,"desc":"<Description>"},{"id":35,"icon":-1,"name":"<Name>","steps":[["<Step>",false,1,1,false]],"rewards":[["item",1,1,false]],"cat":0,"desc":"<Description>"},{"id":36,"icon":-1,"name":"<Name>","steps":[["<Step>",false,1,1,false]],"rewards":[["item",1,1,false]],"cat":0,"desc":"<Description>"},{"id":37,"icon":-1,"name":"<Name>","steps":[["<Step>",false,1,1,false]],"rewards":[["item",1,1,false]],"cat":0,"desc":"<Description>"},{"id":38,"icon":-1,"name":"<Name>","steps":[["<Step>",false,1,1,false]],"rewards":[["item",1,1,false]],"cat":0,"desc":"<Description>"},{"id":39,"icon":-1,"name":"<Name>","steps":[["<Step>",false,1,1,false]],"rewards":[["item",1,1,false]],"cat":0,"desc":"<Description>"},{"id":40,"icon":-1,"name":"<Name>","steps":[["<Step>",false,1,1,false]],"rewards":[["item",1,1,false]],"cat":0,"desc":"<Description>"},{"id":41,"icon":-1,"name":"<Name>","steps":[["<Step>",false,1,1,false]],"rewards":[["item",1,1,false]],"cat":0,"desc":"<Description>"},{"id":42,"icon":-1,"name":"<Name>","steps":[["<Step>",false,1,1,false]],"rewards":[["item",1,1,false]],"cat":0,"desc":"<Description>"},{"id":43,"icon":-1,"name":"<Name>","steps":[["<Step>",false,1,1,false]],"rewards":[["item",1,1,false]],"cat":0,"desc":"<Description>"},{"id":44,"icon":-1,"name":"<Name>","steps":[["<Step>",false,1,1,false]],"rewards":[["item",1,1,false]],"cat":0,"desc":"<Description>"},{"id":45,"icon":-1,"name":"<Name>","steps":[["<Step>",false,1,1,false]],"rewards":[["item",1,1,false]],"cat":0,"desc":"<Description>"},{"id":46,"icon":-1,"name":"<Name>","steps":[["<Step>",false,1,1,false]],"rewards":[["item",1,1,false]],"cat":0,"desc":"<Description>"},{"id":47,"icon":-1,"name":"<Name>","steps":[["<Step>",false,1,1,false]],"rewards":[["item",1,1,false]],"cat":0,"desc":"<Description>"},{"id":48,"icon":-1,"name":"<Name>","steps":[["<Step>",false,1,1,false]],"rewards":[["item",1,1,false]],"cat":0,"desc":"<Description>"},{"id":49,"icon":-1,"name":"<Name>","steps":[["<Step>",false,1,1,false]],"rewards":[["item",1,1,false]],"cat":0,"desc":"<Description>"},{"id":50,"icon":-1,"name":"<Name>","steps":[["<Step>",false,1,1,false]],"rewards":[["item",1,1,false]],"cat":0,"desc":"<Description>"},{"id":51,"icon":-1,"name":"<Name>","steps":[["<Step>",false,1,1,false]],"rewards":[["item",1,1,false]],"cat":0,"desc":"<Description>"},{"id":52,"icon":-1,"name":"<Name>","steps":[["<Step>",false,1,1,false]],"rewards":[["item",1,1,false]],"cat":0,"desc":"<Description>"},{"id":53,"icon":-1,"name":"<Name>","steps":[["<Step>",false,1,1,false]],"rewards":[["item",1,1,false]],"cat":0,"desc":"<Description>"},{"id":54,"icon":-1,"name":"<Name>","steps":[["<Step>",false,1,1,false]],"rewards":[["item",1,1,false]],"cat":0,"desc":"<Description>"},{"id":55,"icon":-1,"name":"<Name>","steps":[["<Step>",false,1,1,false]],"rewards":[["item",1,1,false]],"cat":0,"desc":"<Description>"},{"id":56,"icon":-1,"name":"<Name>","steps":[["<Step>",false,1,1,false]],"rewards":[["item",1,1,false]],"cat":0,"desc":"<Description>"},{"id":57,"icon":-1,"name":"<Name>","steps":[["<Step>",false,1,1,false]],"rewards":[["item",1,1,false]],"cat":0,"desc":"<Description>"},{"id":58,"icon":-1,"name":"<Name>","steps":[["<Step>",false,1,1,false]],"rewards":[["item",1,1,false]],"cat":0,"desc":"<Description>"},{"id":59,"icon":-1,"name":"<Name>","steps":[["<Step>",false,1,1,false]],"rewards":[["item",1,1,false]],"cat":0,"desc":"<Description>"},{"id":60,"icon":-1,"name":"<Name>","steps":[["<Step>",false,1,1,false]],"rewards":[["item",1,1,false]],"cat":0,"desc":"<Description>"},{"id":61,"icon":-1,"name":"<Name>","steps":[["<Step>",false,1,1,false]],"rewards":[["item",1,1,false]],"cat":0,"desc":"<Description>"},{"id":62,"icon":-1,"name":"<Name>","steps":[["<Step>",false,1,1,false]],"rewards":[["item",1,1,false]],"cat":0,"desc":"<Description>"},{"id":63,"icon":-1,"name":"<Name>","steps":[["<Step>",false,1,1,false]],"rewards":[["item",1,1,false]],"cat":0,"desc":"<Description>"},{"id":64,"icon":-1,"name":"<Name>","steps":[["<Step>",false,1,1,false]],"rewards":[["item",1,1,false]],"cat":0,"desc":"<Description>"},{"id":65,"icon":-1,"name":"<Name>","steps":[["<Step>",false,1,1,false]],"rewards":[["item",1,1,false]],"cat":0,"desc":"<Description>"},{"id":66,"icon":-1,"name":"<Name>","steps":[["<Step>",false,1,1,false]],"rewards":[["item",1,1,false]],"cat":0,"desc":"<Description>"},{"id":67,"icon":-1,"name":"<Name>","steps":[["<Step>",false,1,1,false]],"rewards":[["item",1,1,false]],"cat":0,"desc":"<Description>"},{"id":68,"icon":-1,"name":"<Name>","steps":[["<Step>",false,1,1,false]],"rewards":[["item",1,1,false]],"cat":0,"desc":"<Description>"},{"id":69,"icon":-1,"name":"<Name>","steps":[["<Step>",false,1,1,false]],"rewards":[["item",1,1,false]],"cat":0,"desc":"<Description>"},{"id":70,"icon":-1,"name":"<Name>","steps":[["<Step>",false,1,1,false]],"rewards":[["item",1,1,false]],"cat":0,"desc":"<Description>"},{"id":71,"icon":-1,"name":"<Name>","steps":[["<Step>",false,1,1,false]],"rewards":[["item",1,1,false]],"cat":0,"desc":"<Description>"},{"id":72,"icon":-1,"name":"<Name>","steps":[["<Step>",false,1,1,false]],"rewards":[["item",1,1,false]],"cat":0,"desc":"<Description>"},{"id":73,"icon":-1,"name":"<Name>","steps":[["<Step>",false,1,1,false]],"rewards":[["item",1,1,false]],"cat":0,"desc":"<Description>"},{"id":74,"icon":-1,"name":"<Name>","steps":[["<Step>",false,1,1,false]],"rewards":[["item",1,1,false]],"cat":0,"desc":"<Description>"},{"id":75,"icon":-1,"name":"<Name>","steps":[["<Step>",false,1,1,false]],"rewards":[["item",1,1,false]],"cat":0,"desc":"<Description>"},{"id":76,"icon":-1,"name":"<Name>","steps":[["<Step>",false,1,1,false]],"rewards":[["item",1,1,false]],"cat":0,"desc":"<Description>"}]